tasks_loader/__init__.py
tasks_loader/main.py
tasks_loader/models.py
tasks_loader-0.1.1.dist-info/METADATA
tasks_loader-0.1.1.dist-info/WHEEL
tasks_loader-0.1.1.dist-info/top_level.txt
tasks_loader-0.1.1.dist-info/RECORD
