Metadata-Version: 2.1
Name: tasks_loader
Version: 0.1.1
Summary: A module for dynamically creating tasks from CSV files with extensive validation features.
Home-page: https://github.com/glizzykingdreko/tasks-loader
Author: GlizzyKingDreko
Author-email: glizzykingdreko@protonmail.com
Classifier: Development Status :: 3 - Alpha
Classifier: Intended Audience :: Developers
Classifier: Topic :: Software Development :: Libraries :: Python Modules
Classifier: License :: OSI Approved :: MIT License
Classifier: Programming Language :: Python :: 3
Classifier: Programming Language :: Python :: 3.7
Classifier: Programming Language :: Python :: 3.8
Classifier: Programming Language :: Python :: 3.9
Classifier: Programming Language :: Python :: 3.10
Requires-Python: >=3.7
